examplepy/__init__.py
examplepy/module1.py
algs_ixi-0.1.0.dist-info/METADATA
algs_ixi-0.1.0.dist-info/WHEEL
algs_ixi-0.1.0.dist-info/top_level.txt
algs_ixi-0.1.0.dist-info/RECORD
